sealib/__init__.py
sealib/conversion_map.py
sealib/decoder.py
sealib/encoder.py
sealib-1.1.dist-info/METADATA
sealib-1.1.dist-info/WHEEL
sealib-1.1.dist-info/RECORD
