Metadata-Version: 2.4
Name: sealib
Version: 1.1
Summary: A simple text encoder SEA (Simple Encoding Algorithm)
Author-email: "Rayshawn Levy (sneekyfoxx)" <sneekyfoxx09@gmail.com>
Maintainer-email: "Rayshawn Levy (sneekyfoxx)" <sneekyfoxx09@gmail.com>
License-Expression: BSD-3-Clause
Keywords: SEA,algorithm,decoder,encoder,sea
Classifier: Development Status :: 5 - Production/Stable
Classifier: Programming Language :: Python :: 3.12
Classifier: Programming Language :: Python :: 3.13
Requires-Python: >=3.13
